{
  "project_info": {
    "project_number": "481535983895",
    "project_id": "arnichemapp-56ab4",
    "storage_bucket": "arnichemapp-56ab4.appspot.com"
  },
  "client": [
    {
      "client_info": {
        "mobilesdk_app_id": "1:481535983895:android:85a15d45af46749a357752",
        "android_client_info": {
          "package_name": "com.arnichem.arnichem_barcode"
        }
      },
      "oauth_client": [
        {
          "client_id": "481535983895-i45cddi47b1g9n8natvf7d67jbm7u60p.apps.googleusercontent.com",
          "client_type": 3
        }
      ],
      "api_key": [
        {
          "current_key": "AIzaSyAOLp8SW5LzPSJNyva6kl-qgLCUkFE1ct8"
        }
      ],
      "services": {
        "appinvite_service": {
          "other_platform_oauth_client": [
            {
              "client_id": "481535983895-i45cddi47b1g9n8natvf7d67jbm7u60p.apps.googleusercontent.com",
              "client_type": 3
            }
          ]
        }
      }
    }
  ],
  "configuration_version": "1"
}